uefi_development/__init__.py
uefi_development/__main__.py
uefi_development/main.py
uefi_development/conf/target.yaml
uefi_development/utils/__init__.py
uefi_development/utils/load_config.py
uefi_development/utils/run.py
uefi_development/utils/runner.py
uefi_development-0.8.8.dist-info/METADATA
uefi_development-0.8.8.dist-info/WHEEL
uefi_development-0.8.8.dist-info/entry_points.txt
uefi_development-0.8.8.dist-info/top_level.txt
uefi_development-0.8.8.dist-info/RECORD
