Metadata-Version: 2.4
Name: uefi_development
Version: 0.8.8
Summary: A Module to easily create a UEFI development environment!
Home-page: https://github.com/alientools-org/uefi-development
Author: hexzhen3x7
Author-email: hexzhen3x7 <hexzhen3x7@blackzspace.de>
License: MIT
Project-URL: Homepage, https://github.com/alientools-org/uefi_development
Project-URL: Repository, https://github.com/alientools-org/uefi_development
Requires-Python: >=3.6
Requires-Dist: requests>=2.0
Requires-Dist: tqdm
Requires-Dist: coloredlogs
Requires-Dist: pyaml
Dynamic: author
Dynamic: home-page
Dynamic: requires-python
